odoo10_addon_sale_commission_formula-10.0.1.0.1-py2.7-nspkg.pth
odoo/addons/sale_commission_formula/README.rst
odoo/addons/sale_commission_formula/__init__.py
odoo/addons/sale_commission_formula/__manifest__.py
odoo/addons/sale_commission_formula/demo/commission_demo.xml
odoo/addons/sale_commission_formula/i18n/ca.po
odoo/addons/sale_commission_formula/i18n/de.po
odoo/addons/sale_commission_formula/i18n/el_GR.po
odoo/addons/sale_commission_formula/i18n/es.po
odoo/addons/sale_commission_formula/i18n/fi.po
odoo/addons/sale_commission_formula/i18n/fr.po
odoo/addons/sale_commission_formula/i18n/it.po
odoo/addons/sale_commission_formula/i18n/pt.po
odoo/addons/sale_commission_formula/i18n/pt_BR.po
odoo/addons/sale_commission_formula/i18n/pt_PT.po
odoo/addons/sale_commission_formula/i18n/ru.po
odoo/addons/sale_commission_formula/i18n/sale_commission_formula.pot
odoo/addons/sale_commission_formula/i18n/sl.po
odoo/addons/sale_commission_formula/i18n/tr.po
odoo/addons/sale_commission_formula/i18n/tr_TR.po
odoo/addons/sale_commission_formula/i18n/zh_CN.po
odoo/addons/sale_commission_formula/models/__init__.py
odoo/addons/sale_commission_formula/models/sale_commission.py
odoo/addons/sale_commission_formula/models/sale_commission_line_mixin.py
odoo/addons/sale_commission_formula/static/description/icon.png
odoo/addons/sale_commission_formula/static/description/icon.svg
odoo/addons/sale_commission_formula/static/src/css/sale_commission_formula.css
odoo/addons/sale_commission_formula/tests/__init__.py
odoo/addons/sale_commission_formula/tests/test_commission_formula.py
odoo/addons/sale_commission_formula/views/sale_commission_view.xml
odoo10_addon_sale_commission_formula-10.0.1.0.1.dist-info/METADATA
odoo10_addon_sale_commission_formula-10.0.1.0.1.dist-info/RECORD
odoo10_addon_sale_commission_formula-10.0.1.0.1.dist-info/WHEEL
odoo10_addon_sale_commission_formula-10.0.1.0.1.dist-info/namespace_packages.txt
odoo10_addon_sale_commission_formula-10.0.1.0.1.dist-info/top_level.txt
