Metadata-Version: 2.1
Name: odoo10-addon-sale-commission-formula
Version: 10.0.1.0.1
Summary: Sale commissions computed by formulas
Home-page: https://github.com/OCA/commission/tree/10.0/sale_commission_formula
Author: Abstract,Odoo Community Association (OCA)
Author-email: support@odoo-community.org
License: AGPL-3
Platform: UNKNOWN
Classifier: Programming Language :: Python
Classifier: Framework :: Odoo
Classifier: License :: OSI Approved :: GNU Affero General Public License v3
Requires-Python: ~=2.7
Requires-Dist: odoo10-addon-sale-commission
Requires-Dist: odoo (<10.1dev,>=10.0)
